odoo9_addon_openeducat_l10n_in-9.0.2.4.0-py2.7-nspkg.pth
odoo9_addon_openeducat_l10n_in-9.0.2.4.0.dist-info/top_level.txt
odoo9_addon_openeducat_l10n_in-9.0.2.4.0.dist-info/WHEEL
odoo9_addon_openeducat_l10n_in-9.0.2.4.0.dist-info/RECORD
odoo9_addon_openeducat_l10n_in-9.0.2.4.0.dist-info/metadata.json
odoo9_addon_openeducat_l10n_in-9.0.2.4.0.dist-info/DESCRIPTION.rst
odoo9_addon_openeducat_l10n_in-9.0.2.4.0.dist-info/METADATA
odoo9_addon_openeducat_l10n_in-9.0.2.4.0.dist-info/namespace_packages.txt
odoo_addons/openeducat_l10n_in/__openerp__.py
odoo_addons/openeducat_l10n_in/__init__.py
odoo_addons/openeducat_l10n_in/security/ir.model.access.csv
odoo_addons/openeducat_l10n_in/models/religion.py
odoo_addons/openeducat_l10n_in/models/__init__.py
odoo_addons/openeducat_l10n_in/models/student.py
odoo_addons/openeducat_l10n_in/models/faculty.py
odoo_addons/openeducat_l10n_in/models/category.py
odoo_addons/openeducat_l10n_in/i18n/openeducat_l10n_in.pot
odoo_addons/openeducat_l10n_in/views/student_view.xml
odoo_addons/openeducat_l10n_in/views/category_view.xml
odoo_addons/openeducat_l10n_in/views/faculty_view.xml
odoo_addons/openeducat_l10n_in/views/religion_view.xml
odoo_addons/openeducat_l10n_in/demo/op.category.csv
odoo_addons/openeducat_l10n_in/demo/op.religion.csv
odoo_addons/openeducat_l10n_in/demo/op.student.csv
odoo_addons/openeducat_l10n_in/demo/op.faculty.csv
odoo_addons/openeducat_l10n_in/static/description/openeducat_logo.png
odoo_addons/openeducat_l10n_in/static/description/l10in.png
odoo_addons/openeducat_l10n_in/static/description/indian_openeducat_banner.jpg
odoo_addons/openeducat_l10n_in/static/description/index.html
odoo_addons/openeducat_l10n_in/static/description/icon.png
